scraper/__init__.py
scraper/src/__init__.py
scraper/src/custom_downloader_middleware.py
scraper/src/custom_dupefilter.py
scraper/src/documentation_spider.py
scraper/src/helpers.py
scraper/src/index.py
scraper/src/js_executor.py
scraper/src/meilisearch_helper.py
scraper/src/config/__init__.py
scraper/src/config/browser_handler.py
scraper/src/config/config_loader.py
scraper/src/config/config_validator.py
scraper/src/config/selectors_parser.py
scraper/src/config/urls_parser.py
scraper/src/config/version.py
scraper/src/strategies/__init__.py
scraper/src/strategies/abstract_strategy.py
scraper/src/strategies/anchor.py
scraper/src/strategies/default_strategy.py
scraper/src/strategies/hierarchy.py
pymeilisearch_scraper-0.2.3.dist-info/WHEEL
pymeilisearch_scraper-0.2.3.dist-info/METADATA
pymeilisearch_scraper-0.2.3.dist-info/RECORD
