Metadata-Version: 2.1
Name: pymeilisearch-scraper
Version: 0.2.3
Summary: Documentation scrapper for PyMeilisearch
Author-email: "ANSYS, Inc." <pyansys.core@ansys.com>
Maintainer-email: "ANSYS, Inc." <pyansys.core@ansys.com>
Requires-Python: >=3.8
Classifier: Development Status :: 4 - Beta
Classifier: Intended Audience :: Science/Research
Classifier: Topic :: Scientific/Engineering :: Information Analysis
Classifier: License :: OSI Approved :: MIT License
Classifier: Operating System :: Microsoft :: Windows
Classifier: Operating System :: POSIX
Classifier: Operating System :: MacOS
Classifier: Programming Language :: Python :: 3.8
Classifier: Programming Language :: Python :: 3.9
Classifier: Programming Language :: Python :: 3.10
Classifier: Programming Language :: Python :: 3.11
Requires-Dist: Scrapy==2.11.0
Requires-Dist: selenium==4.10.0
Requires-Dist: requests-iap==0.2.0
Requires-Dist: meilisearch==0.28.2
Requires-Dist: requests==2.31.0
Requires-Dist: python-keycloak-client==0.2.3
Requires-Dist: pytest==7.2.0 ; extra == "dev"
Requires-Dist: pylint==2.15.9 ; extra == "dev"
Requires-Dist: tox==3.27.1 ; extra == "dev"
Requires-Dist: tox-pipenv==1.10.1 ; extra == "dev"
Project-URL: Homepage, https://github.com/ansys/pymeilisearch-scraper
Project-URL: Source, https://github.com/ansys/pymeilisearch-scraper
Project-URL: Tracker, https://github.com/ansys/pymeilisearch-scraper/issues
Provides-Extra: dev
